remoteinference/__init__.py
remoteinference/interfaces/__init__.py
remoteinference/interfaces/llm.py
remoteinference/models/__init__.py
remoteinference/models/models.py
remoteinference/util/__init__.py
remoteinference/util/config.py
remoteinference-0.0.2.dist-info/METADATA
remoteinference-0.0.2.dist-info/WHEEL
remoteinference-0.0.2.dist-info/top_level.txt
remoteinference-0.0.2.dist-info/RECORD
